hollow/__init__.py
hollow/cli.py
hollow/logics.py
hollow-0.1.0.dist-info/LICENSE.txt
hollow-0.1.0.dist-info/METADATA
hollow-0.1.0.dist-info/WHEEL
hollow-0.1.0.dist-info/entry_points.txt
hollow-0.1.0.dist-info/top_level.txt
hollow-0.1.0.dist-info/RECORD
