Metadata-Version: 2.2
Name: hollow
Version: 0.1.0
Summary: Hollow Knight Save Modifier CLI
Home-page: https://github.com/Andy-0x0/Hollow-Knight-Save-Editor-CLI
Author: Tianyi Ma
Author-email: tym.andy777@gmail.com
License: GPL-3.0
Classifier: Programming Language :: Python :: 3
Classifier: License :: OSI Approved :: GNU General Public License v3 (GPLv3)
Classifier: Operating System :: OS Independent
Requires-Python: >=3.7
License-File: LICENSE.txt
Requires-Dist: pycryptodome
Dynamic: author
Dynamic: author-email
Dynamic: classifier
Dynamic: description-content-type
Dynamic: home-page
Dynamic: license
Dynamic: requires-dist
Dynamic: requires-python
Dynamic: summary
